kiertotie/__init__.py
kiertotie/__main__.py
kiertotie/cli.py
kiertotie/dispatch.py
kiertotie/elif.py
kiertotie/tree.py
kiertotie/update.py
kiertotie-2023.1.5.dist-info/LICENSE
kiertotie-2023.1.5.dist-info/METADATA
kiertotie-2023.1.5.dist-info/WHEEL
kiertotie-2023.1.5.dist-info/entry_points.txt
kiertotie-2023.1.5.dist-info/top_level.txt
kiertotie-2023.1.5.dist-info/RECORD
