Metadata-Version: 2.1
Name: kiertotie
Version: 2023.1.5
Summary: Detour (Finnish: kiertotie) per rsync proxy to https mirror node.
Author-email: Stefan Hagen <stefan@hagen.link>
Maintainer-email: Stefan Hagen <stefan@hagen.link>
Project-URL: Homepage, https://git.sr.ht/~sthagen/kiertotie
Project-URL: Bug-Tracker, https://todo.sr.ht/~sthagen/kiertotie
Project-URL: Documentation, https://codes.dilettant.life/docs/kiertotie
Project-URL: Source-Code, https://git.sr.ht/~sthagen/kiertotie
Project-URL: Test-Coverage, https://codes.dilettant.life/coverage/kiertotie
Keywords: developer-tools,validation,verification
Classifier: Development Status :: 3 - Alpha
Classifier: Intended Audience :: Developers
Classifier: License :: OSI Approved :: MIT License
Classifier: Programming Language :: Python :: 3.10
Classifier: Programming Language :: Python :: 3.11
Requires-Python: >=3.10
License-File: LICENSE
Requires-Dist: Babel (>=2.11.0)
Requires-Dist: PyYAML (>=6.0)
Requires-Dist: typer (>=0.7.0)
Provides-Extra: dev
Requires-Dist: black ; extra == 'dev'
Requires-Dist: coverage ; extra == 'dev'
Requires-Dist: hypothesis ; extra == 'dev'
Requires-Dist: mypy ; extra == 'dev'
Requires-Dist: pytest ; extra == 'dev'
Requires-Dist: pytest-cov ; extra == 'dev'
Requires-Dist: pytest-flake8 ; extra == 'dev'
Requires-Dist: ruff ; extra == 'dev'
